pyautomagic/__init__.py
pyautomagic/base/__init__.py
pyautomagic/preprocessing/__init__.py
pyautomagic/preprocessing/performFilter.py
pyautomagic/preprocessing/perform_EOG_regression.py
pyautomagic/preprocessing/preprocess.py
pyautomagic/preprocessing/rpca.py
pyautomagic/src/Block.py
pyautomagic/src/Config.py
pyautomagic/src/Project.py
pyautomagic/src/Subject.py
pyautomagic/src/__init__.py
pyautomagic/src/calcQuality.py
pyautomagic/src/rateQuality.py
pyautomagic/visualization/__init__.py
tests/pipeline/__init__.py
tests/pyautomagic/__init__.py
tests/pyautomagic/testRateQuality.py
tests/pyautomagic/test_EOG_Regression.py
tests/pyautomagic/test_Subject.py
tests/pyautomagic/test_block.py
tests/pyautomagic/test_calcQuality.py
tests/pyautomagic/test_dummy.py
tests/pyautomagic/test_performEOGRegression.py
tests/pyautomagic/test_performFilt.py
tests/pyautomagic/test_performRPCA.py
tests/pyautomagic/test_preprocess.py
tests/pyautomagic/test_project.py
pyautomagic-0.1.0.dist-info/LICENSE
pyautomagic-0.1.0.dist-info/METADATA
pyautomagic-0.1.0.dist-info/WHEEL
pyautomagic-0.1.0.dist-info/dependency_links.txt
pyautomagic-0.1.0.dist-info/top_level.txt
pyautomagic-0.1.0.dist-info/RECORD
