Metadata-Version: 2.1
Name: pyautomagic
Version: 0.1.0
Summary: A Python3 package for eeg (pre)processing from Automagic.
Home-page: https://github.com/NeuroDataDesign/pyautomagic
Author: NDD19
Maintainer: Adam Li
Maintainer-email: adam2392@gmail.com
License: MIT
Project-URL: Documentation, https://github.com/NeuroDataDesign/pyautomagic/docs/
Project-URL: Source, https://github.com/NeuroDataDesign/pyautomagic
Project-URL: Tracker, https://github.com/NeuroDataDesign/pyautomagic/issues
Keywords: EEG,research tools,automated processing
Platform: UNKNOWN
Classifier: Development Status :: 3 - Alpha
Classifier: Intended Audience :: Developers
Classifier: Intended Audience :: Science/Research
Classifier: Topic :: Scientific/Engineering :: Medical Science Apps.
Classifier: Topic :: Scientific/Engineering
Classifier: Programming Language :: Python :: 3.6
Classifier: Programming Language :: Python :: 3.7
Classifier: Programming Language :: Python :: Implementation
Classifier: Natural Language :: English
Requires-Dist: numpy (>=1.14.5)
Requires-Dist: scipy (>=1.1.0)
Requires-Dist: scikit-learn (>=0.19.2)
Requires-Dist: pandas (>=0.23.4)
Requires-Dist: mne (>=0.19.2)
Requires-Dist: mne-bids (>=0.3)
